karbon/__init__.py
karbon/__main__.py
karbon/_version.py
karbon/karbon.py
karbon-0.3.0.dist-info/licenses/LICENSE
karbon-0.3.0.dist-info/METADATA
karbon-0.3.0.dist-info/WHEEL
karbon-0.3.0.dist-info/entry_points.txt
karbon-0.3.0.dist-info/top_level.txt
karbon-0.3.0.dist-info/RECORD
