Metadata-Version: 2.4
Name: karbon
Version: 0.3.0
Summary: Turn mouse events into art!
Author-email: Furkan Onder <furkanonder@protonmail.com>
Maintainer-email: Furkan Onder <furkanonder@protonmail.com>, Bahadır Araz <bahadiraraz@protonmail.com>
License: MIT
Project-URL: Homepage, https://github.com/furkanonder/karbon
Project-URL: Documentation, https://github.com/furkanonder/karbon#readme
Project-URL: Repository, https://github.com/furkanonder/karbon
Project-URL: Bug Reports, https://github.com/furkanonder/karbon/issues
Project-URL: Changelog, https://github.com/furkanonder/karbon/blob/main/CHANGELOG.MD
Project-URL: Funding, https://github.com/sponsors/furkanonder
Keywords: mouse tracking,mouse,tracking,art,visualization,graphics,pygame,drawing
Classifier: Development Status :: 3 - Alpha
Classifier: Intended Audience :: End Users/Desktop
Classifier: Intended Audience :: Developers
Classifier: License :: OSI Approved :: MIT License
Classifier: Operating System :: OS Independent
Classifier: Programming Language :: Python
Classifier: Programming Language :: Python :: 3 :: Only
Classifier: Programming Language :: Python :: 3.10
Classifier: Programming Language :: Python :: 3.11
Classifier: Programming Language :: Python :: 3.12
Classifier: Programming Language :: Python :: 3.13
Classifier: Topic :: Games/Entertainment
Classifier: Topic :: Multimedia :: Graphics
Classifier: Topic :: Multimedia :: Graphics :: Capture :: Screen Capture
Classifier: Topic :: Multimedia :: Graphics :: Graphics Conversion
Classifier: Topic :: Artistic Software
Classifier: Topic :: Desktop Environment
Classifier: Topic :: System :: Monitoring
Classifier: Natural Language :: English
Requires-Python: >=3.10
License-File: LICENSE
Requires-Dist: pygame-ce==2.5.5
Requires-Dist: pygame-gui==0.6.14
Requires-Dist: pynput==1.8.1
Requires-Dist: screeninfo>=0.8.1
Provides-Extra: dev
Requires-Dist: pre-commit>=4.3.0; extra == "dev"
Requires-Dist: tox>=4.30.2; extra == "dev"
Requires-Dist: mypy>=1.18.2; extra == "dev"
Requires-Dist: ruff>=0.13.1; extra == "dev"
Requires-Dist: pytest>=8.4.2; extra == "dev"
Dynamic: license-file
